clearskies_akeyless_custom_wiz/__init__.py
clearskies_akeyless_custom_wiz/create.py
clearskies_akeyless_custom_wiz/rotate.py
clear_skies_akeyless_custom_wiz-2.0.7.dist-info/METADATA
clear_skies_akeyless_custom_wiz-2.0.7.dist-info/WHEEL
clear_skies_akeyless_custom_wiz-2.0.7.dist-info/licenses/LICENSE
clear_skies_akeyless_custom_wiz-2.0.7.dist-info/RECORD
