Metadata-Version: 2.4
Name: clear-skies-akeyless-custom-wiz
Version: 2.0.7
Summary: Akeyless+Clearskies Custom Wiz Producer/Rotator
Project-URL: repository, https://github.com/clearskies-akeyless-custom-producers/wiz
Project-URL: Issues, https://github.com/clearskies-akeyless-custom-producers/wiz/issues
Project-URL: Changelog, https://github.com/clearskies-akeyless-custom-producers/wiz/blob/main/CHANGELOG.md
Author-email: Conor Mancone <cmancone@gmail.com>
License-Expression: MIT
License-File: LICENSE
Classifier: Development Status :: 5 - Production/Stable
Classifier: Intended Audience :: Developers
Classifier: License :: OSI Approved :: MIT License
Classifier: Programming Language :: Python :: 3
Requires-Python: <4.0,>=3.11
Requires-Dist: clear-skies-akeyless-custom-producer<3.0.0,>=2.0.0
Requires-Dist: requests<3.0.0,>=2.0.0
Provides-Extra: dev
Requires-Dist: black>=25.1.0; extra == 'dev'
Requires-Dist: mypy>=1.16.1; extra == 'dev'
Requires-Dist: pre-commit>=3.8.0; extra == 'dev'
Requires-Dist: pytest>=8.4.1; extra == 'dev'
Requires-Dist: ruff>=0.12.1; extra == 'dev'
Requires-Dist: types-requests>=2.32.4; extra == 'dev'
